{   "dataset_type" : "ffhq",
    "params_dict":{
    "pop art": {
        "clip_global": 10000,
        "clip_dir": 20000,
        "l_zecon" : 50,
        "l_mse": 1000,
        "l_vgg": 50,
        "patch_max": 0.3,
        "t_0": 25
    },
    "stone wall": 
    {
        "clip_global": 2000,
        "clip_dir": 50000,
        "l_zecon" : 500,
        "l_mse": 5000,
        "l_vgg": 10,
        "patch_max": 0.1,
        "t_0": 25
    },
    "tanned face": 
    {
        "clip_global": 15000,
        "clip_dir": 15000,
        "l_zecon" : 1000,
        "l_mse": 10000,
        "l_vgg": 100,
        "patch_max": 0.3,
        "t_0": 25
    },
    "clay": {
        "clip_global": 40000,
        "clip_dir": 40000,
        "l_zecon" : 1000,
        "l_mse": 10000,
        "l_vgg": 0,
        "patch_max": 0.05,
        "t_0": 25
    },
    "portrait by Gogh": 
    {
        "clip_global": 10000,
        "clip_dir": 7000,
        "l_zecon" : 10,
        "l_mse": 3000,
        "l_vgg": 50,
        "patch_max": 0.3,
        "t_0": 25
    },
    "a sketch with crayon": 
    {
        "clip_global": 10000,
        "clip_dir": 20000,
        "l_zecon" : 500,
        "l_mse": 10000,
        "l_vgg": 100,
        "patch_max": 0.3,
        "t_0": 25
    }, 
    "3d render in the style of Pixar": 
    {
        "clip_global": 5000,
        "clip_dir": 5000,
        "l_zecon" : 500,
        "l_mse": 10000,
        "l_vgg": 100,
        "patch_max": 0.3,
        "t_0": 25
    },
    "golden": 
    {
        "clip_global": 7000,
        "clip_dir": 7000,
        "l_zecon" : 200,
        "l_mse": 0,
        "l_vgg": 50,
        "patch_max": 0.05,
        "t_0": 15
    },
    "ukiyo-e": 
    {
        "clip_global": 8000,
        "clip_dir": 20000,
        "l_zecon" : 1000,
        "l_mse": 5000,
        "l_vgg": 100,
        "patch_max": 0.3,
        "t_0": 25
    },
    "marbling": 
    {
        "clip_global": 20000,
        "clip_dir": 40000,
        "l_zecon" : 1000,
        "l_mse": 10000,
        "l_vgg": 10,
        "patch_max": 0.3,
        "t_0": 25
    }
    }
}
